{
  "eslint": "eslint",
  "i18next": "i18next",
  "jest": "jest",
  "react": "react",
  "sass": "sass",
  "typescript": "typescript",
  "webpack": "webpack",
  "Базовая конфигурация реакт приложения": "Базовая конфигурация реакт приложения",
  "Будьте осторожны со своими желаниями, ибо они имеют тенденцию сбываться": "Будьте осторожны со своими желаниями, ибо они имеют тенденцию сбываться",
  "Все желания нарушающие правила, будут удалены": "Все желания нарушающие правила, будут удалены",
  "Добавить": "Добавить",
  "Добавьте свою историю": "Добавьте свою историю",
  "Желания": "Желания",
  "Желания смерти, увечий и т": {
    " д": {
      "": "Желания смерти, увечий и т. д."
    }
  },
  "Желания смерти, увечий и так далее": "Желания смерти, увечий и так далее",
  "Загадай желание": "Загадай желание",
  "Здесь вы можете загадать свое желание, каким бы странным оно не было": "Здесь вы можете загадать свое желание, каким бы странным оно не было",
  "Истории": "Истории",
  "Напишите свое желание": {
    "": {
      "": {
        "": ""
      }
    }
  },
  "Не разрешено": "Не разрешено",
  "Нецензурные слова": "Нецензурные слова",
  "Оскорбления": "Оскорбления",
  "Правила": "Правила",
  "Унижение в любых формах": "Унижение в любых формах",
  "Читать еще": "Читать еще",
  "Что используется": "Что используется"
}
